[
  {
    "uuid": "0b208b50-18b6-409f-a7d6-1a798cbe5f57",
    "name": "VxrpixeltTV",
    "note": "https://forum.griefergames.de/forum/thread/452632-vxrpixelttv-grieft-das-grundst%C3%BCck-von-der187fan/",
    "createdAt": "2024-07-17T17:34:28.113534851",
    "updatedAt": "2024-07-17T17:34:28.113572906",
    "duration": 180
  },
  {
    "uuid": "17024667-9a4c-47c5-9c2c-02215790e778",
    "name": "NadalAdler",
    "note": "https://forum.griefergames.de/forum/thread/450448-nadaladler-benutzt-sein-twitch-stream-um-die-community-zu-scammen-f%C3%BCr-casino-zoc/",
    "createdAt": "2024-07-06T09:54:02.162604093",
    "updatedAt": "2024-07-06T09:54:02.162614804",
    "duration": 180
  },
  {
    "uuid": "1a7ff479-9309-4962-b6ff-e678640704e6",
    "name": "Pegagasus",
    "note": "https://forum.griefergames.de/forum/thread/445184-pegagasus-versuct-mit-fake-money-mm-trade-zu-bedienen/",
    "createdAt": "2024-05-25T07:21:44.457528802",
    "updatedAt": "2024-05-25T07:21:44.45755379",
    "duration": 180
  },
  {
    "uuid": "226b2b90-934b-462a-b8e1-1dde297798c7",
    "name": "Oussagaza",
    "note": "https://forum.griefergames.de/forum/thread/450791-pr3ctical-scammt-um-150k/",
    "createdAt": "2024-07-07T07:58:25.98842987",
    "updatedAt": "2024-07-18T17:33:49.806392481",
    "duration": 180
  },
  {
    "uuid": "330f46f1-6ced-4938-8751-8fa7c1b83964",
    "name": "Absafter",
    "note": "https://forum.griefergames.de/forum/thread/457728-achtung-vor-paddy-05z-er-scamt-beweise-unten/",
    "createdAt": "2024-09-10T14:20:56.498581412",
    "updatedAt": "2024-10-16T20:37:21.9442581",
    "duration": 180
  },
  {
    "uuid": "375267b6-2f95-479e-9bae-d766c61fd029",
    "name": "ploombir",
    "note": "https://forum.griefergames.de/forum/thread/455039-kaka-essen-123-scammt/",
    "createdAt": "2024-08-12T21:28:02.098400501",
    "updatedAt": "2024-09-25T16:20:41.293699427",
    "duration": 180
  },
  {
    "uuid": "3ca5731e-730c-47d8-beb8-0aa6371f284f",
    "name": "4DPommes",
    "note": "https://forum.griefergames.de/forum/thread/460911-4dpommes-verkauft-luckykisten-umbenannt/",
    "createdAt": "2024-10-14T21:12:24.686773528",
    "updatedAt": "2024-10-14T21:12:24.686788807",
    "duration": 180
  },
  {
    "uuid": "50965cb8-472b-4767-9164-5476aa9a83e3",
    "name": "ibraim8910",
    "note": "https://forum.griefergames.de/forum/thread/451195-scammer-ibraim8910/",
    "createdAt": "2024-07-07T08:00:49.458146203",
    "updatedAt": "2024-07-07T08:00:49.458158507",
    "duration": 180
  },
  {
    "uuid": "5bd8a68d-5108-41d7-b65a-e868c17b30cc",
    "name": "ZEN_Chistofeles",
    "note": "https://forum.griefergames.de/forum/thread/456716-marhdi-scammt-um-8mio-prefix-mit-bett-trick/",
    "createdAt": "2024-08-28T22:14:01.600999566",
    "updatedAt": "2024-09-02T23:17:23.558966947",
    "duration": 180
  },
  {
    "uuid": "5c31002d-6890-4260-8738-c8c947a396a9",
    "name": "A0G_Bot",
    "note": "https://forum.griefergames.de/forum/thread/450907-mxwtuu/",
    "createdAt": "2024-07-07T07:57:38.440018863",
    "updatedAt": "2024-07-25T19:34:01.95809007",
    "duration": 180
  },
  {
    "uuid": "5f347afa-6e7e-44e9-9c10-0f3cef11d56d",
    "name": "VeyytexOnFire",
    "note": "https://cdn.discordapp.com/attachments/1269607691882332170/1269609376218484756/image.png?ex\u003d66b54c9f\u0026is\u003d66b3fb1f\u0026hm\u003d0a9631339570698401bbfe64a3b88b867d270660d73ac5c6b7a594ea2700b3cc\u0026",
    "createdAt": "2024-08-08T02:48:48.526478038",
    "updatedAt": "2024-08-08T02:48:48.526506683",
    "duration": 180
  },
  {
    "uuid": "65049a1a-b458-4753-82ad-2389d4b26f97",
    "name": "DerKeksKlauer",
    "note": "https://forum.griefergames.de/forum/thread/440073-derkeksklauer/",
    "createdAt": "2024-05-23T14:21:00.102656314",
    "updatedAt": "2024-05-23T20:51:03.139756462",
    "duration": 180
  },
  {
    "uuid": "8d0225e2-2f75-337e-a6a7-47364ba8e8c7",
    "name": "!Sus8909",
    "note": "https://forum.griefergames.de/forum/thread/452732-warnung-vor-dem-spieler-sus8909/",
    "createdAt": "2024-07-18T00:20:11.573946916",
    "updatedAt": "2024-07-18T00:20:11.573954701",
    "duration": 180
  },
  {
    "uuid": "8e822d1d-392d-4666-9e3e-8d4a250320a8",
    "name": "zSkela",
    "note": "https://discord.com/channels/1147881225692917780/1278446057461776424",
    "createdAt": "2024-08-29T20:08:46.003288663",
    "updatedAt": "2024-08-29T20:08:46.003290366",
    "duration": 180
  },
  {
    "uuid": "a2057463-f707-4190-b3c2-05e10f7c5fbc",
    "name": "ByLyntex",
    "note": "https://forum.griefergames.de/forum/thread/456850-auktionshaus-fake-supreme-r%C3%A4nge/",
    "createdAt": "2024-08-29T20:10:14.33259974",
    "updatedAt": "2024-08-29T20:10:14.332601573",
    "duration": 180
  },
  {
    "uuid": "ab96e62d-abdc-4b81-9443-fdc9a257103a",
    "name": "Feuerstahin_",
    "note": "https://forum.griefergames.de/forum/thread/442024-airwaves-scammt/",
    "createdAt": "2024-05-25T02:04:55.662452824",
    "updatedAt": "2024-07-20T19:33:46.247763725",
    "duration": 180
  },
  {
    "uuid": "c9c6e172-37b4-4635-9857-c3eec08e0813",
    "name": "RZXVB",
    "note": "https://forum.griefergames.de/forum/thread/458118-rzxvb-scammt-und-begeht-danach-rufmord-an-focaccia16/",
    "createdAt": "2024-09-19T23:40:49.670849575",
    "updatedAt": "2024-09-19T23:40:49.670852481",
    "duration": 180
  },
  {
    "uuid": "d6b43301-6b14-4f1b-8e7e-5993028142da",
    "name": "Trubs4Life",
    "note": "https://forum.griefergames.de/forum/thread/460993-scamming-mit-umbenannten-kisten/",
    "createdAt": "2024-10-14T21:11:08.54499122",
    "updatedAt": "2024-10-14T21:11:08.545054544",
    "duration": 180
  },
  {
    "uuid": "db53d648-f360-4290-a9a5-cd6bb738553c",
    "name": "shrkyx",
    "note": "https://forum.griefergames.de/forum/thread/452035-mxnu027-scam-bei-poseidon-casino/",
    "createdAt": "2024-07-15T13:52:05.60113571",
    "updatedAt": "2024-07-15T13:52:05.60114605",
    "duration": 180
  },
  {
    "uuid": "f000dc08-4d30-31bb-8d9d-38cd2e0fedd2",
    "name": "!CapitolBot",
    "note": "https://forum.griefergames.de/forum/thread/454492-sammelbeitrag-alle-auktionshaus-scammer/?pageNo\u003d1",
    "createdAt": "2024-08-05T23:42:54.935348842",
    "updatedAt": "2024-08-05T23:42:54.935356677",
    "duration": 180
  },
  {
    "uuid": "f04c3294-9ee9-4af7-a841-9bb1aeee13d3",
    "name": "Elite_Lasse",
    "note": "https://forum.griefergames.de/forum/thread/455309-elite-lasse-scammt-um-20-000/",
    "createdAt": "2024-08-12T21:21:44.494370349",
    "updatedAt": "2024-08-12T21:21:44.494381561",
    "duration": 180
  }
]